qadence_libs/__init__.py
qadence_libs/types.py
qadence_libs/constructors/__init__.py
qadence_libs/constructors/feature_maps.py
qadence_libs/constructors/hea.py
qadence_libs/constructors/iia.py
qadence_libs/constructors/qft.py
qadence_libs/constructors/rydberg_feature_maps.py
qadence_libs/constructors/rydberg_hea.py
qadence_libs/constructors/utils.py
qadence_libs/qinfo_tools/__init__.py
qadence_libs/qinfo_tools/qfi.py
qadence_libs/qinfo_tools/qng.py
qadence_libs/qinfo_tools/spsa.py
qadence_libs/qinfo_tools/utils.py
qadence_libs-0.1.3.dist-info/METADATA
qadence_libs-0.1.3.dist-info/WHEEL
qadence_libs-0.1.3.dist-info/licenses/LICENSE
qadence_libs-0.1.3.dist-info/RECORD
