Metadata-Version: 2.3
Name: qadence-libs
Version: 0.1.3
Summary: Libraries to extend Qadence functionalities.
Author-email: Mario Dagrada <mario.dagrada@pasqal.com>, Roland Guichard <roland.guichard@pasqal.com>, João Moutinho <joao.moutinho@pasqal.com>, Vincent Elfving <vincent.elfving@pasqal.com>, Dominik Seitz <dominik.seitz@pasqal.com>, Niklas Heim <niklas.heim@pasqal.com>, Ignacio Fernández Graña <ignacio.fernandez-grana@pasqal.com>
License: Apache 2.0
License-File: LICENSE
Keywords: quantum
Classifier: License :: OSI Approved :: Apache Software License
Classifier: Programming Language :: Python
Classifier: Programming Language :: Python :: 3
Classifier: Programming Language :: Python :: 3.9
Classifier: Programming Language :: Python :: 3.10
Classifier: Programming Language :: Python :: 3.11
Classifier: Programming Language :: Python :: Implementation :: CPython
Classifier: Programming Language :: Python :: Implementation :: PyPy
Requires-Python: <3.12,>=3.9
Requires-Dist: qadence[braket,horqrux,pulser]
Requires-Dist: torch
Provides-Extra: visualization
Requires-Dist: graphviz; extra == 'visualization'
